basic_robotics/__init__.py
basic_robotics/general/__init__.py
basic_robotics/general/faser_general.py
basic_robotics/general/faser_high_performance.py
basic_robotics/general/faser_transform.py
basic_robotics/interfaces/Communications.py
basic_robotics/interfaces/__init__.py
basic_robotics/kinematics/__init__.py
basic_robotics/kinematics/arm_model.py
basic_robotics/kinematics/sp_model.py
basic_robotics/modern_robotics_numba/__init__.py
basic_robotics/modern_robotics_numba/modern_high_performance.py
basic_robotics/path_planning/__init__.py
basic_robotics/path_planning/pathplanner.py
basic_robotics/plotting/Draw.py
basic_robotics/plotting/__init__.py
basic_robotics/robot_collisions/__init__.py
basic_robotics/robot_collisions/collision_manager.py
basic_robotics/utilities/FaserLog.py
basic_robotics/utilities/__init__.py
basic_robotics/utilities/disp.py
basic_robotics-0.2.14.dist-info/LICENSE
basic_robotics-0.2.14.dist-info/METADATA
basic_robotics-0.2.14.dist-info/WHEEL
basic_robotics-0.2.14.dist-info/top_level.txt
basic_robotics-0.2.14.dist-info/RECORD
