Metadata-Version: 2.1
Name: basic-robotics
Version: 0.2.14
Summary: Basic Robotics Toolbox Developed in FASER Lab
Home-page: https://github.com/64-B1T/basic_robotics
Author: William Chapin
Author-email: liam@64b1t.com
License: MIT
Platform: UNKNOWN
License-File: LICENSE
Requires-Dist: numpy (<=1.21.5,>=1.19)
Requires-Dist: pyserial
Requires-Dist: scipy
Requires-Dist: numba
Requires-Dist: modern-robotics
Requires-Dist: numpy-stl
Requires-Dist: descartes
Requires-Dist: alphashape
Requires-Dist: trimesh
Requires-Dist: rtree
